cd_dynamic_versioning/__init__.py
cd_dynamic_versioning-0.0.6.dist-info/METADATA
cd_dynamic_versioning-0.0.6.dist-info/WHEEL
cd_dynamic_versioning-0.0.6.dist-info/RECORD
