Metadata-Version: 2.1
Name: cd-dynamic-versioning
Version: 0.0.6
Summary: Testpackage for dynamic versioning
License: MIT
Author: Yngve Moe
Author-email: yngve.m.moe@gmail.com
Requires-Python: >=3.8.1,<4.0
Classifier: License :: OSI Approved :: MIT License
Classifier: Programming Language :: Python :: 3
Classifier: Programming Language :: Python :: 3.9
Classifier: Programming Language :: Python :: 3.10
Classifier: Programming Language :: Python :: 3.11
